RoboHashpy/RoboHashpy.py
RoboHashpy/__init__.py
RoboHashpy-0.1.1.dist-info/METADATA
RoboHashpy-0.1.1.dist-info/WHEEL
RoboHashpy-0.1.1.dist-info/top_level.txt
RoboHashpy-0.1.1.dist-info/RECORD
